{
  "meta": {
    "last_updated": "2026-06-24",
    "n_simulations": 1000,
    "show_conditional": true
  },
  "teams": [
    {
      "team_id": 798,
      "team_name": "Czechia",
      "group": "A",
      "outcomes": [
        {
          "matchday_3_result": "win",
          "n_sims": 290,
          "p_1st": 0.0,
          "p_2nd": 0.2483,
          "p_3rd": 0.7517,
          "p_4th": 0.0,
          "p_advances": 1.0
        },
        {
          "matchday_3_result": "draw",
          "n_sims": 259,
          "p_1st": 0.0,
          "p_2nd": 0.0,
          "p_3rd": 0.7645,
          "p_4th": 0.2355,
          "p_advances": 0.0116
        },
        {
          "matchday_3_result": "loss",
          "n_sims": 451,
          "p_1st": 0.0,
          "p_2nd": 0.0,
          "p_3rd": 0.4213,
          "p_4th": 0.5787,
          "p_advances": 0.0
        }
      ]
    },
    {
      "team_id": 769,
      "team_name": "Mexico",
      "group": "A",
      "outcomes": [
        {
          "matchday_3_result": "win",
          "n_sims": 451,
          "p_1st": 1.0,
          "p_2nd": 0.0,
          "p_3rd": 0.0,
          "p_4th": 0.0,
          "p_advances": 1.0
        },
        {
          "matchday_3_result": "draw",
          "n_sims": 259,
          "p_1st": 1.0,
          "p_2nd": 0.0,
          "p_3rd": 0.0,
          "p_4th": 0.0,
          "p_advances": 1.0
        },
        {
          "matchday_3_result": "loss",
          "n_sims": 290,
          "p_1st": 1.0,
          "p_2nd": 0.0,
          "p_3rd": 0.0,
          "p_4th": 0.0,
          "p_advances": 1.0
        }
      ]
    },
    {
      "team_id": 774,
      "team_name": "South Africa",
      "group": "A",
      "outcomes": [
        {
          "matchday_3_result": "win",
          "n_sims": 268,
          "p_1st": 0.0,
          "p_2nd": 0.7313,
          "p_3rd": 0.2687,
          "p_4th": 0.0,
          "p_advances": 1.0
        },
        {
          "matchday_3_result": "draw",
          "n_sims": 266,
          "p_1st": 0.0,
          "p_2nd": 0.0,
          "p_3rd": 0.4135,
          "p_4th": 0.5865,
          "p_advances": 0.0038
        },
        {
          "matchday_3_result": "loss",
          "n_sims": 466,
          "p_1st": 0.0,
          "p_2nd": 0.0,
          "p_3rd": 0.0558,
          "p_4th": 0.9442,
          "p_advances": 0.0
        }
      ]
    },
    {
      "team_id": 772,
      "team_name": "South Korea",
      "group": "A",
      "outcomes": [
        {
          "matchday_3_result": "win",
          "n_sims": 466,
          "p_1st": 0.0,
          "p_2nd": 1.0,
          "p_3rd": 0.0,
          "p_4th": 0.0,
          "p_advances": 1.0
        },
        {
          "matchday_3_result": "draw",
          "n_sims": 266,
          "p_1st": 0.0,
          "p_2nd": 1.0,
          "p_3rd": 0.0,
          "p_4th": 0.0,
          "p_advances": 1.0
        },
        {
          "matchday_3_result": "loss",
          "n_sims": 268,
          "p_1st": 0.0,
          "p_2nd": 0.0,
          "p_3rd": 0.694,
          "p_4th": 0.306,
          "p_advances": 0.5075
        }
      ]
    },
    {
      "team_id": 764,
      "team_name": "Brazil",
      "group": "C",
      "outcomes": [
        {
          "matchday_3_result": "win",
          "n_sims": 461,
          "p_1st": 0.9696,
          "p_2nd": 0.0304,
          "p_3rd": 0.0,
          "p_4th": 0.0,
          "p_advances": 1.0
        },
        {
          "matchday_3_result": "draw",
          "n_sims": 238,
          "p_1st": 0.4622,
          "p_2nd": 0.5378,
          "p_3rd": 0.0,
          "p_4th": 0.0,
          "p_advances": 1.0
        },
        {
          "matchday_3_result": "loss",
          "n_sims": 301,
          "p_1st": 0.0,
          "p_2nd": 0.2292,
          "p_3rd": 0.7708,
          "p_4th": 0.0,
          "p_advances": 1.0
        }
      ]
    },
    {
      "team_id": 836,
      "team_name": "Haiti",
      "group": "C",
      "outcomes": [
        {
          "matchday_3_result": "win",
          "n_sims": 259,
          "p_1st": 0.0,
          "p_2nd": 0.0,
          "p_3rd": 0.0,
          "p_4th": 1.0,
          "p_advances": 0.0
        },
        {
          "matchday_3_result": "draw",
          "n_sims": 243,
          "p_1st": 0.0,
          "p_2nd": 0.0,
          "p_3rd": 0.0,
          "p_4th": 1.0,
          "p_advances": 0.0
        },
        {
          "matchday_3_result": "loss",
          "n_sims": 498,
          "p_1st": 0.0,
          "p_2nd": 0.0,
          "p_3rd": 0.0,
          "p_4th": 1.0,
          "p_advances": 0.0
        }
      ]
    },
    {
      "team_id": 815,
      "team_name": "Morocco",
      "group": "C",
      "outcomes": [
        {
          "matchday_3_result": "win",
          "n_sims": 498,
          "p_1st": 0.5743,
          "p_2nd": 0.4257,
          "p_3rd": 0.0,
          "p_4th": 0.0,
          "p_advances": 1.0
        },
        {
          "matchday_3_result": "draw",
          "n_sims": 243,
          "p_1st": 0.0,
          "p_2nd": 1.0,
          "p_3rd": 0.0,
          "p_4th": 0.0,
          "p_advances": 1.0
        },
        {
          "matchday_3_result": "loss",
          "n_sims": 259,
          "p_1st": 0.0,
          "p_2nd": 0.7336,
          "p_3rd": 0.2664,
          "p_4th": 0.0,
          "p_advances": 1.0
        }
      ]
    },
    {
      "team_id": 8873,
      "team_name": "Scotland",
      "group": "C",
      "outcomes": [
        {
          "matchday_3_result": "win",
          "n_sims": 301,
          "p_1st": 0.5216,
          "p_2nd": 0.4784,
          "p_3rd": 0.0,
          "p_4th": 0.0,
          "p_advances": 1.0
        },
        {
          "matchday_3_result": "draw",
          "n_sims": 238,
          "p_1st": 0.0,
          "p_2nd": 0.0,
          "p_3rd": 1.0,
          "p_4th": 0.0,
          "p_advances": 1.0
        },
        {
          "matchday_3_result": "loss",
          "n_sims": 461,
          "p_1st": 0.0,
          "p_2nd": 0.0,
          "p_3rd": 1.0,
          "p_4th": 0.0,
          "p_advances": 0.6963
        }
      ]
    },
    {
      "team_id": 779,
      "team_name": "Australia",
      "group": "D",
      "outcomes": [
        {
          "matchday_3_result": "win",
          "n_sims": 451,
          "p_1st": 0.0,
          "p_2nd": 1.0,
          "p_3rd": 0.0,
          "p_4th": 0.0,
          "p_advances": 1.0
        },
        {
          "matchday_3_result": "draw",
          "n_sims": 263,
          "p_1st": 0.0,
          "p_2nd": 1.0,
          "p_3rd": 0.0,
          "p_4th": 0.0,
          "p_advances": 1.0
        },
        {
          "matchday_3_result": "loss",
          "n_sims": 286,
          "p_1st": 0.0,
          "p_2nd": 0.0,
          "p_3rd": 1.0,
          "p_4th": 0.0,
          "p_advances": 0.7413
        }
      ]
    },
    {
      "team_id": 761,
      "team_name": "Paraguay",
      "group": "D",
      "outcomes": [
        {
          "matchday_3_result": "win",
          "n_sims": 286,
          "p_1st": 0.0,
          "p_2nd": 1.0,
          "p_3rd": 0.0,
          "p_4th": 0.0,
          "p_advances": 1.0
        },
        {
          "matchday_3_result": "draw",
          "n_sims": 263,
          "p_1st": 0.0,
          "p_2nd": 0.0,
          "p_3rd": 1.0,
          "p_4th": 0.0,
          "p_advances": 0.9962
        },
        {
          "matchday_3_result": "loss",
          "n_sims": 451,
          "p_1st": 0.0,
          "p_2nd": 0.0,
          "p_3rd": 1.0,
          "p_4th": 0.0,
          "p_advances": 0.3814
        }
      ]
    },
    {
      "team_id": 803,
      "team_name": "Turkey",
      "group": "D",
      "outcomes": [
        {
          "matchday_3_result": "win",
          "n_sims": 324,
          "p_1st": 0.0,
          "p_2nd": 0.0,
          "p_3rd": 0.0,
          "p_4th": 1.0,
          "p_advances": 0.0
        },
        {
          "matchday_3_result": "draw",
          "n_sims": 246,
          "p_1st": 0.0,
          "p_2nd": 0.0,
          "p_3rd": 0.0,
          "p_4th": 1.0,
          "p_advances": 0.0
        },
        {
          "matchday_3_result": "loss",
          "n_sims": 430,
          "p_1st": 0.0,
          "p_2nd": 0.0,
          "p_3rd": 0.0,
          "p_4th": 1.0,
          "p_advances": 0.0
        }
      ]
    },
    {
      "team_id": 771,
      "team_name": "United States",
      "group": "D",
      "outcomes": [
        {
          "matchday_3_result": "win",
          "n_sims": 430,
          "p_1st": 1.0,
          "p_2nd": 0.0,
          "p_3rd": 0.0,
          "p_4th": 0.0,
          "p_advances": 1.0
        },
        {
          "matchday_3_result": "draw",
          "n_sims": 246,
          "p_1st": 1.0,
          "p_2nd": 0.0,
          "p_3rd": 0.0,
          "p_4th": 0.0,
          "p_advances": 1.0
        },
        {
          "matchday_3_result": "loss",
          "n_sims": 324,
          "p_1st": 1.0,
          "p_2nd": 0.0,
          "p_3rd": 0.0,
          "p_4th": 0.0,
          "p_advances": 1.0
        }
      ]
    },
    {
      "team_id": 9460,
      "team_name": "Cura\u00e7ao",
      "group": "E",
      "outcomes": [
        {
          "matchday_3_result": "win",
          "n_sims": 283,
          "p_1st": 0.0,
          "p_2nd": 0.6678,
          "p_3rd": 0.3322,
          "p_4th": 0.0,
          "p_advances": 0.9965
        },
        {
          "matchday_3_result": "draw",
          "n_sims": 287,
          "p_1st": 0.0,
          "p_2nd": 0.0,
          "p_3rd": 0.3275,
          "p_4th": 0.6725,
          "p_advances": 0.0
        },
        {
          "matchday_3_result": "loss",
          "n_sims": 430,
          "p_1st": 0.0,
          "p_2nd": 0.0,
          "p_3rd": 0.0,
          "p_4th": 1.0,
          "p_advances": 0.0
        }
      ]
    },
    {
      "team_id": 791,
      "team_name": "Ecuador",
      "group": "E",
      "outcomes": [
        {
          "matchday_3_result": "win",
          "n_sims": 345,
          "p_1st": 0.0,
          "p_2nd": 0.2725,
          "p_3rd": 0.7275,
          "p_4th": 0.0,
          "p_advances": 1.0
        },
        {
          "matchday_3_result": "draw",
          "n_sims": 254,
          "p_1st": 0.0,
          "p_2nd": 0.0,
          "p_3rd": 0.7441,
          "p_4th": 0.2559,
          "p_advances": 0.0157
        },
        {
          "matchday_3_result": "loss",
          "n_sims": 401,
          "p_1st": 0.0,
          "p_2nd": 0.0,
          "p_3rd": 0.4564,
          "p_4th": 0.5436,
          "p_advances": 0.0
        }
      ]
    },
    {
      "team_id": 759,
      "team_name": "Germany",
      "group": "E",
      "outcomes": [
        {
          "matchday_3_result": "win",
          "n_sims": 401,
          "p_1st": 1.0,
          "p_2nd": 0.0,
          "p_3rd": 0.0,
          "p_4th": 0.0,
          "p_advances": 1.0
        },
        {
          "matchday_3_result": "draw",
          "n_sims": 254,
          "p_1st": 1.0,
          "p_2nd": 0.0,
          "p_3rd": 0.0,
          "p_4th": 0.0,
          "p_advances": 1.0
        },
        {
          "matchday_3_result": "loss",
          "n_sims": 345,
          "p_1st": 1.0,
          "p_2nd": 0.0,
          "p_3rd": 0.0,
          "p_4th": 0.0,
          "p_advances": 1.0
        }
      ]
    },
    {
      "team_id": 1935,
      "team_name": "Ivory Coast",
      "group": "E",
      "outcomes": [
        {
          "matchday_3_result": "win",
          "n_sims": 430,
          "p_1st": 0.0,
          "p_2nd": 1.0,
          "p_3rd": 0.0,
          "p_4th": 0.0,
          "p_advances": 1.0
        },
        {
          "matchday_3_result": "draw",
          "n_sims": 287,
          "p_1st": 0.0,
          "p_2nd": 1.0,
          "p_3rd": 0.0,
          "p_4th": 0.0,
          "p_advances": 1.0
        },
        {
          "matchday_3_result": "loss",
          "n_sims": 283,
          "p_1st": 0.0,
          "p_2nd": 0.0,
          "p_3rd": 0.6678,
          "p_4th": 0.3322,
          "p_advances": 0.523
        }
      ]
    },
    {
      "team_id": 766,
      "team_name": "Japan",
      "group": "F",
      "outcomes": [
        {
          "matchday_3_result": "win",
          "n_sims": 427,
          "p_1st": 0.6979,
          "p_2nd": 0.3021,
          "p_3rd": 0.0,
          "p_4th": 0.0,
          "p_advances": 1.0
        },
        {
          "matchday_3_result": "draw",
          "n_sims": 267,
          "p_1st": 0.3371,
          "p_2nd": 0.6629,
          "p_3rd": 0.0,
          "p_4th": 0.0,
          "p_advances": 1.0
        },
        {
          "matchday_3_result": "loss",
          "n_sims": 306,
          "p_1st": 0.0,
          "p_2nd": 0.1405,
          "p_3rd": 0.8595,
          "p_4th": 0.0,
          "p_advances": 1.0
        }
      ]
    },
    {
      "team_id": 8601,
      "team_name": "Netherlands",
      "group": "F",
      "outcomes": [
        {
          "matchday_3_result": "win",
          "n_sims": 445,
          "p_1st": 0.8404,
          "p_2nd": 0.1596,
          "p_3rd": 0.0,
          "p_4th": 0.0,
          "p_advances": 1.0
        },
        {
          "matchday_3_result": "draw",
          "n_sims": 248,
          "p_1st": 0.2056,
          "p_2nd": 0.7944,
          "p_3rd": 0.0,
          "p_4th": 0.0,
          "p_advances": 1.0
        },
        {
          "matchday_3_result": "loss",
          "n_sims": 307,
          "p_1st": 0.0,
          "p_2nd": 0.8599,
          "p_3rd": 0.1401,
          "p_4th": 0.0,
          "p_advances": 1.0
        }
      ]
    },
    {
      "team_id": 792,
      "team_name": "Sweden",
      "group": "F",
      "outcomes": [
        {
          "matchday_3_result": "win",
          "n_sims": 306,
          "p_1st": 0.6111,
          "p_2nd": 0.3889,
          "p_3rd": 0.0,
          "p_4th": 0.0,
          "p_advances": 1.0
        },
        {
          "matchday_3_result": "draw",
          "n_sims": 267,
          "p_1st": 0.0,
          "p_2nd": 0.0,
          "p_3rd": 1.0,
          "p_4th": 0.0,
          "p_advances": 1.0
        },
        {
          "matchday_3_result": "loss",
          "n_sims": 427,
          "p_1st": 0.0,
          "p_2nd": 0.0,
          "p_3rd": 1.0,
          "p_4th": 0.0,
          "p_advances": 0.8665
        }
      ]
    },
    {
      "team_id": 802,
      "team_name": "Tunisia",
      "group": "F",
      "outcomes": [
        {
          "matchday_3_result": "win",
          "n_sims": 307,
          "p_1st": 0.0,
          "p_2nd": 0.0,
          "p_3rd": 0.0,
          "p_4th": 1.0,
          "p_advances": 0.0
        },
        {
          "matchday_3_result": "draw",
          "n_sims": 248,
          "p_1st": 0.0,
          "p_2nd": 0.0,
          "p_3rd": 0.0,
          "p_4th": 1.0,
          "p_advances": 0.0
        },
        {
          "matchday_3_result": "loss",
          "n_sims": 445,
          "p_1st": 0.0,
          "p_2nd": 0.0,
          "p_3rd": 0.0,
          "p_4th": 1.0,
          "p_advances": 0.0
        }
      ]
    },
    {
      "team_id": 805,
      "team_name": "Belgium",
      "group": "G",
      "outcomes": [
        {
          "matchday_3_result": "win",
          "n_sims": 547,
          "p_1st": 0.1974,
          "p_2nd": 0.8026,
          "p_3rd": 0.0,
          "p_4th": 0.0,
          "p_advances": 1.0
        },
        {
          "matchday_3_result": "draw",
          "n_sims": 232,
          "p_1st": 0.0,
          "p_2nd": 0.3448,
          "p_3rd": 0.6552,
          "p_4th": 0.0,
          "p_advances": 0.9612
        },
        {
          "matchday_3_result": "loss",
          "n_sims": 221,
          "p_1st": 0.0,
          "p_2nd": 0.0,
          "p_3rd": 0.181,
          "p_4th": 0.819,
          "p_advances": 0.0
        }
      ]
    },
    {
      "team_id": 825,
      "team_name": "Egypt",
      "group": "G",
      "outcomes": [
        {
          "matchday_3_result": "win",
          "n_sims": 384,
          "p_1st": 1.0,
          "p_2nd": 0.0,
          "p_3rd": 0.0,
          "p_4th": 0.0,
          "p_advances": 1.0
        },
        {
          "matchday_3_result": "draw",
          "n_sims": 237,
          "p_1st": 0.8945,
          "p_2nd": 0.1055,
          "p_3rd": 0.0,
          "p_4th": 0.0,
          "p_advances": 1.0
        },
        {
          "matchday_3_result": "loss",
          "n_sims": 379,
          "p_1st": 0.0,
          "p_2nd": 0.4697,
          "p_3rd": 0.5303,
          "p_4th": 0.0,
          "p_advances": 1.0
        }
      ]
    },
    {
      "team_id": 840,
      "team_name": "Iran",
      "group": "G",
      "outcomes": [
        {
          "matchday_3_result": "win",
          "n_sims": 379,
          "p_1st": 0.781,
          "p_2nd": 0.219,
          "p_3rd": 0.0,
          "p_4th": 0.0,
          "p_advances": 1.0
        },
        {
          "matchday_3_result": "draw",
          "n_sims": 237,
          "p_1st": 0.0,
          "p_2nd": 0.2363,
          "p_3rd": 0.7637,
          "p_4th": 0.0,
          "p_advances": 0.9831
        },
        {
          "matchday_3_result": "loss",
          "n_sims": 384,
          "p_1st": 0.0,
          "p_2nd": 0.0,
          "p_3rd": 0.8125,
          "p_4th": 0.1875,
          "p_advances": 0.0104
        }
      ]
    },
    {
      "team_id": 783,
      "team_name": "New Zealand",
      "group": "G",
      "outcomes": [
        {
          "matchday_3_result": "win",
          "n_sims": 221,
          "p_1st": 0.0,
          "p_2nd": 0.629,
          "p_3rd": 0.371,
          "p_4th": 0.0,
          "p_advances": 1.0
        },
        {
          "matchday_3_result": "draw",
          "n_sims": 232,
          "p_1st": 0.0,
          "p_2nd": 0.0,
          "p_3rd": 0.1379,
          "p_4th": 0.8621,
          "p_advances": 0.0
        },
        {
          "matchday_3_result": "loss",
          "n_sims": 547,
          "p_1st": 0.0,
          "p_2nd": 0.0,
          "p_3rd": 0.0,
          "p_4th": 1.0,
          "p_advances": 0.0
        }
      ]
    },
    {
      "team_id": 1930,
      "team_name": "Cape Verde Islands",
      "group": "H",
      "outcomes": [
        {
          "matchday_3_result": "win",
          "n_sims": 359,
          "p_1st": 0.1086,
          "p_2nd": 0.8914,
          "p_3rd": 0.0,
          "p_4th": 0.0,
          "p_advances": 1.0
        },
        {
          "matchday_3_result": "draw",
          "n_sims": 267,
          "p_1st": 0.0,
          "p_2nd": 0.4419,
          "p_3rd": 0.5581,
          "p_4th": 0.0,
          "p_advances": 0.97
        },
        {
          "matchday_3_result": "loss",
          "n_sims": 374,
          "p_1st": 0.0,
          "p_2nd": 0.0,
          "p_3rd": 0.2139,
          "p_4th": 0.7861,
          "p_advances": 0.0027
        }
      ]
    },
    {
      "team_id": 801,
      "team_name": "Saudi Arabia",
      "group": "H",
      "outcomes": [
        {
          "matchday_3_result": "win",
          "n_sims": 374,
          "p_1st": 0.0,
          "p_2nd": 0.6872,
          "p_3rd": 0.3128,
          "p_4th": 0.0,
          "p_advances": 0.9947
        },
        {
          "matchday_3_result": "draw",
          "n_sims": 267,
          "p_1st": 0.0,
          "p_2nd": 0.0,
          "p_3rd": 0.0075,
          "p_4th": 0.9925,
          "p_advances": 0.0
        },
        {
          "matchday_3_result": "loss",
          "n_sims": 359,
          "p_1st": 0.0,
          "p_2nd": 0.0,
          "p_3rd": 0.0,
          "p_4th": 1.0,
          "p_advances": 0.0
        }
      ]
    },
    {
      "team_id": 760,
      "team_name": "Spain",
      "group": "H",
      "outcomes": [
        {
          "matchday_3_result": "win",
          "n_sims": 437,
          "p_1st": 1.0,
          "p_2nd": 0.0,
          "p_3rd": 0.0,
          "p_4th": 0.0,
          "p_advances": 1.0
        },
        {
          "matchday_3_result": "draw",
          "n_sims": 240,
          "p_1st": 1.0,
          "p_2nd": 0.0,
          "p_3rd": 0.0,
          "p_4th": 0.0,
          "p_advances": 1.0
        },
        {
          "matchday_3_result": "loss",
          "n_sims": 323,
          "p_1st": 0.0,
          "p_2nd": 0.6471,
          "p_3rd": 0.3529,
          "p_4th": 0.0,
          "p_advances": 1.0
        }
      ]
    },
    {
      "team_id": 758,
      "team_name": "Uruguay",
      "group": "H",
      "outcomes": [
        {
          "matchday_3_result": "win",
          "n_sims": 323,
          "p_1st": 0.8793,
          "p_2nd": 0.1207,
          "p_3rd": 0.0,
          "p_4th": 0.0,
          "p_advances": 1.0
        },
        {
          "matchday_3_result": "draw",
          "n_sims": 240,
          "p_1st": 0.0,
          "p_2nd": 0.2375,
          "p_3rd": 0.7625,
          "p_4th": 0.0,
          "p_advances": 0.9875
        },
        {
          "matchday_3_result": "loss",
          "n_sims": 437,
          "p_1st": 0.0,
          "p_2nd": 0.0,
          "p_3rd": 0.8124,
          "p_4th": 0.1876,
          "p_advances": 0.0366
        }
      ]
    },
    {
      "team_id": 773,
      "team_name": "France",
      "group": "I",
      "outcomes": [
        {
          "matchday_3_result": "win",
          "n_sims": 505,
          "p_1st": 1.0,
          "p_2nd": 0.0,
          "p_3rd": 0.0,
          "p_4th": 0.0,
          "p_advances": 1.0
        },
        {
          "matchday_3_result": "draw",
          "n_sims": 230,
          "p_1st": 1.0,
          "p_2nd": 0.0,
          "p_3rd": 0.0,
          "p_4th": 0.0,
          "p_advances": 1.0
        },
        {
          "matchday_3_result": "loss",
          "n_sims": 265,
          "p_1st": 0.0,
          "p_2nd": 1.0,
          "p_3rd": 0.0,
          "p_4th": 0.0,
          "p_advances": 1.0
        }
      ]
    },
    {
      "team_id": 8062,
      "team_name": "Iraq",
      "group": "I",
      "outcomes": [
        {
          "matchday_3_result": "win",
          "n_sims": 324,
          "p_1st": 0.0,
          "p_2nd": 0.0,
          "p_3rd": 1.0,
          "p_4th": 0.0,
          "p_advances": 0.2747
        },
        {
          "matchday_3_result": "draw",
          "n_sims": 266,
          "p_1st": 0.0,
          "p_2nd": 0.0,
          "p_3rd": 0.0,
          "p_4th": 1.0,
          "p_advances": 0.0
        },
        {
          "matchday_3_result": "loss",
          "n_sims": 410,
          "p_1st": 0.0,
          "p_2nd": 0.0,
          "p_3rd": 0.0,
          "p_4th": 1.0,
          "p_advances": 0.0
        }
      ]
    },
    {
      "team_id": 8872,
      "team_name": "Norway",
      "group": "I",
      "outcomes": [
        {
          "matchday_3_result": "win",
          "n_sims": 265,
          "p_1st": 1.0,
          "p_2nd": 0.0,
          "p_3rd": 0.0,
          "p_4th": 0.0,
          "p_advances": 1.0
        },
        {
          "matchday_3_result": "draw",
          "n_sims": 230,
          "p_1st": 0.0,
          "p_2nd": 1.0,
          "p_3rd": 0.0,
          "p_4th": 0.0,
          "p_advances": 1.0
        },
        {
          "matchday_3_result": "loss",
          "n_sims": 505,
          "p_1st": 0.0,
          "p_2nd": 1.0,
          "p_3rd": 0.0,
          "p_4th": 0.0,
          "p_advances": 1.0
        }
      ]
    },
    {
      "team_id": 804,
      "team_name": "Senegal",
      "group": "I",
      "outcomes": [
        {
          "matchday_3_result": "win",
          "n_sims": 410,
          "p_1st": 0.0,
          "p_2nd": 0.0,
          "p_3rd": 1.0,
          "p_4th": 0.0,
          "p_advances": 0.7707
        },
        {
          "matchday_3_result": "draw",
          "n_sims": 266,
          "p_1st": 0.0,
          "p_2nd": 0.0,
          "p_3rd": 1.0,
          "p_4th": 0.0,
          "p_advances": 0.0
        },
        {
          "matchday_3_result": "loss",
          "n_sims": 324,
          "p_1st": 0.0,
          "p_2nd": 0.0,
          "p_3rd": 0.0,
          "p_4th": 1.0,
          "p_advances": 0.0
        }
      ]
    },
    {
      "team_id": 778,
      "team_name": "Algeria",
      "group": "J",
      "outcomes": [
        {
          "matchday_3_result": "win",
          "n_sims": 328,
          "p_1st": 0.0,
          "p_2nd": 1.0,
          "p_3rd": 0.0,
          "p_4th": 0.0,
          "p_advances": 1.0
        },
        {
          "matchday_3_result": "draw",
          "n_sims": 263,
          "p_1st": 0.0,
          "p_2nd": 0.0,
          "p_3rd": 1.0,
          "p_4th": 0.0,
          "p_advances": 0.9962
        },
        {
          "matchday_3_result": "loss",
          "n_sims": 409,
          "p_1st": 0.0,
          "p_2nd": 0.0,
          "p_3rd": 1.0,
          "p_4th": 0.0,
          "p_advances": 0.4132
        }
      ]
    },
    {
      "team_id": 762,
      "team_name": "Argentina",
      "group": "J",
      "outcomes": [
        {
          "matchday_3_result": "win",
          "n_sims": 540,
          "p_1st": 1.0,
          "p_2nd": 0.0,
          "p_3rd": 0.0,
          "p_4th": 0.0,
          "p_advances": 1.0
        },
        {
          "matchday_3_result": "draw",
          "n_sims": 222,
          "p_1st": 1.0,
          "p_2nd": 0.0,
          "p_3rd": 0.0,
          "p_4th": 0.0,
          "p_advances": 1.0
        },
        {
          "matchday_3_result": "loss",
          "n_sims": 238,
          "p_1st": 1.0,
          "p_2nd": 0.0,
          "p_3rd": 0.0,
          "p_4th": 0.0,
          "p_advances": 1.0
        }
      ]
    },
    {
      "team_id": 816,
      "team_name": "Austria",
      "group": "J",
      "outcomes": [
        {
          "matchday_3_result": "win",
          "n_sims": 409,
          "p_1st": 0.0,
          "p_2nd": 1.0,
          "p_3rd": 0.0,
          "p_4th": 0.0,
          "p_advances": 1.0
        },
        {
          "matchday_3_result": "draw",
          "n_sims": 263,
          "p_1st": 0.0,
          "p_2nd": 1.0,
          "p_3rd": 0.0,
          "p_4th": 0.0,
          "p_advances": 1.0
        },
        {
          "matchday_3_result": "loss",
          "n_sims": 328,
          "p_1st": 0.0,
          "p_2nd": 0.0,
          "p_3rd": 1.0,
          "p_4th": 0.0,
          "p_advances": 0.7927
        }
      ]
    },
    {
      "team_id": 8049,
      "team_name": "Jordan",
      "group": "J",
      "outcomes": [
        {
          "matchday_3_result": "win",
          "n_sims": 238,
          "p_1st": 0.0,
          "p_2nd": 0.0,
          "p_3rd": 0.0,
          "p_4th": 1.0,
          "p_advances": 0.0
        },
        {
          "matchday_3_result": "draw",
          "n_sims": 222,
          "p_1st": 0.0,
          "p_2nd": 0.0,
          "p_3rd": 0.0,
          "p_4th": 1.0,
          "p_advances": 0.0
        },
        {
          "matchday_3_result": "loss",
          "n_sims": 540,
          "p_1st": 0.0,
          "p_2nd": 0.0,
          "p_3rd": 0.0,
          "p_4th": 1.0,
          "p_advances": 0.0
        }
      ]
    },
    {
      "team_id": 818,
      "team_name": "Colombia",
      "group": "K",
      "outcomes": [
        {
          "matchday_3_result": "win",
          "n_sims": 376,
          "p_1st": 1.0,
          "p_2nd": 0.0,
          "p_3rd": 0.0,
          "p_4th": 0.0,
          "p_advances": 1.0
        },
        {
          "matchday_3_result": "draw",
          "n_sims": 206,
          "p_1st": 1.0,
          "p_2nd": 0.0,
          "p_3rd": 0.0,
          "p_4th": 0.0,
          "p_advances": 1.0
        },
        {
          "matchday_3_result": "loss",
          "n_sims": 418,
          "p_1st": 0.0,
          "p_2nd": 1.0,
          "p_3rd": 0.0,
          "p_4th": 0.0,
          "p_advances": 1.0
        }
      ]
    },
    {
      "team_id": 1934,
      "team_name": "Congo DR",
      "group": "K",
      "outcomes": [
        {
          "matchday_3_result": "win",
          "n_sims": 378,
          "p_1st": 0.0,
          "p_2nd": 0.0106,
          "p_3rd": 0.9894,
          "p_4th": 0.0,
          "p_advances": 1.0
        },
        {
          "matchday_3_result": "draw",
          "n_sims": 294,
          "p_1st": 0.0,
          "p_2nd": 0.0,
          "p_3rd": 1.0,
          "p_4th": 0.0,
          "p_advances": 0.0272
        },
        {
          "matchday_3_result": "loss",
          "n_sims": 328,
          "p_1st": 0.0,
          "p_2nd": 0.0,
          "p_3rd": 0.0,
          "p_4th": 1.0,
          "p_advances": 0.0
        }
      ]
    },
    {
      "team_id": 765,
      "team_name": "Portugal",
      "group": "K",
      "outcomes": [
        {
          "matchday_3_result": "win",
          "n_sims": 418,
          "p_1st": 1.0,
          "p_2nd": 0.0,
          "p_3rd": 0.0,
          "p_4th": 0.0,
          "p_advances": 1.0
        },
        {
          "matchday_3_result": "draw",
          "n_sims": 206,
          "p_1st": 0.0,
          "p_2nd": 1.0,
          "p_3rd": 0.0,
          "p_4th": 0.0,
          "p_advances": 1.0
        },
        {
          "matchday_3_result": "loss",
          "n_sims": 376,
          "p_1st": 0.0,
          "p_2nd": 0.9894,
          "p_3rd": 0.0106,
          "p_4th": 0.0,
          "p_advances": 1.0
        }
      ]
    },
    {
      "team_id": 8070,
      "team_name": "Uzbekistan",
      "group": "K",
      "outcomes": [
        {
          "matchday_3_result": "win",
          "n_sims": 328,
          "p_1st": 0.0,
          "p_2nd": 0.0,
          "p_3rd": 1.0,
          "p_4th": 0.0,
          "p_advances": 0.1707
        },
        {
          "matchday_3_result": "draw",
          "n_sims": 294,
          "p_1st": 0.0,
          "p_2nd": 0.0,
          "p_3rd": 0.0,
          "p_4th": 1.0,
          "p_advances": 0.0
        },
        {
          "matchday_3_result": "loss",
          "n_sims": 378,
          "p_1st": 0.0,
          "p_2nd": 0.0,
          "p_3rd": 0.0,
          "p_4th": 1.0,
          "p_advances": 0.0
        }
      ]
    },
    {
      "team_id": 799,
      "team_name": "Croatia",
      "group": "L",
      "outcomes": [
        {
          "matchday_3_result": "win",
          "n_sims": 467,
          "p_1st": 0.5096,
          "p_2nd": 0.4904,
          "p_3rd": 0.0,
          "p_4th": 0.0,
          "p_advances": 1.0
        },
        {
          "matchday_3_result": "draw",
          "n_sims": 256,
          "p_1st": 0.0,
          "p_2nd": 0.0,
          "p_3rd": 1.0,
          "p_4th": 0.0,
          "p_advances": 1.0
        },
        {
          "matchday_3_result": "loss",
          "n_sims": 277,
          "p_1st": 0.0,
          "p_2nd": 0.0,
          "p_3rd": 1.0,
          "p_4th": 0.0,
          "p_advances": 0.6859
        }
      ]
    },
    {
      "team_id": 770,
      "team_name": "England",
      "group": "L",
      "outcomes": [
        {
          "matchday_3_result": "win",
          "n_sims": 495,
          "p_1st": 0.9778,
          "p_2nd": 0.0222,
          "p_3rd": 0.0,
          "p_4th": 0.0,
          "p_advances": 1.0
        },
        {
          "matchday_3_result": "draw",
          "n_sims": 207,
          "p_1st": 0.2705,
          "p_2nd": 0.7295,
          "p_3rd": 0.0,
          "p_4th": 0.0,
          "p_advances": 1.0
        },
        {
          "matchday_3_result": "loss",
          "n_sims": 298,
          "p_1st": 0.0,
          "p_2nd": 0.9597,
          "p_3rd": 0.0403,
          "p_4th": 0.0,
          "p_advances": 1.0
        }
      ]
    },
    {
      "team_id": 763,
      "team_name": "Ghana",
      "group": "L",
      "outcomes": [
        {
          "matchday_3_result": "win",
          "n_sims": 277,
          "p_1st": 0.5271,
          "p_2nd": 0.4729,
          "p_3rd": 0.0,
          "p_4th": 0.0,
          "p_advances": 1.0
        },
        {
          "matchday_3_result": "draw",
          "n_sims": 256,
          "p_1st": 0.2969,
          "p_2nd": 0.7031,
          "p_3rd": 0.0,
          "p_4th": 0.0,
          "p_advances": 1.0
        },
        {
          "matchday_3_result": "loss",
          "n_sims": 467,
          "p_1st": 0.0,
          "p_2nd": 0.0257,
          "p_3rd": 0.9743,
          "p_4th": 0.0,
          "p_advances": 1.0
        }
      ]
    },
    {
      "team_id": 1836,
      "team_name": "Panama",
      "group": "L",
      "outcomes": [
        {
          "matchday_3_result": "win",
          "n_sims": 298,
          "p_1st": 0.0,
          "p_2nd": 0.0,
          "p_3rd": 0.0,
          "p_4th": 1.0,
          "p_advances": 0.0
        },
        {
          "matchday_3_result": "draw",
          "n_sims": 207,
          "p_1st": 0.0,
          "p_2nd": 0.0,
          "p_3rd": 0.0,
          "p_4th": 1.0,
          "p_advances": 0.0
        },
        {
          "matchday_3_result": "loss",
          "n_sims": 495,
          "p_1st": 0.0,
          "p_2nd": 0.0,
          "p_3rd": 0.0,
          "p_4th": 1.0,
          "p_advances": 0.0
        }
      ]
    }
  ]
}